[
  {
    "word": "le lycée",
    "translation": "das Gymnasium, die gymnasiale Oberstufe"
  },
  {
    "word": "revenir",
    "translation": "zurückkommen"
  },
  {
    "word": "évidemment",
    "translation": "natürlich, selbstverständlich"
  },
  {
    "word": "le site web",
    "translation": "die Webseite"
  },
  {
    "word": "correspondre à",
    "translation": "entsprechen"
  },
  {
    "word": "la seconde",
    "translation": "wörtl.: die zweite, erstes Jahr der Oberstufe"
  },
  {
    "word": "la famille d'accueil",
    "translation": "die Gastfamilie"
  },
  {
    "word": "absolument",
    "translation": "ganz, unbedingt"
  },
  {
    "word": "gentiment",
    "translation": "netterweise"
  },
  {
    "word": "mot à mot",
    "translation": "wortwörtlich"
  },
  {
    "word": "même si",
    "translation": "auch wenn, selbst wenn"
  },
  {
    "word": "éclater de rire",
    "translation": "in Lachen ausbrechen"
  },
  {
    "word": "couramment",
    "translation": "fließend"
  },
  {
    "word": "énormément",
    "translation": "sehr viel, gewaltig"
  },
  {
    "word": "le progrès",
    "translation": "der Fortschritt"
  },
  {
    "word": "le séjour",
    "translation": "der Aufenthalt"
  },
  {
    "word": "différemment",
    "translation": "anders"
  },
  {
    "word": "de manière ...",
    "translation": "auf ... Art und Weise"
  },
  {
    "word": "être assis",
    "translation": "sitzen"
  },
  {
    "word": "faire le tour de qc",
    "translation": "um etw. herumgehen"
  },
  {
    "word": "pas grand-chose",
    "translation": "nicht viel, nichts Besonderes"
  },
  {
    "word": "le carnet de correspondance",
    "translation": "das Mitteilungsheft"
  },
  {
    "word": "carrément",
    "translation": "total, direkt"
  },
  {
    "word": "s'entendre",
    "translation": "sich verstehen"
  },
  {
    "word": "pourtant",
    "translation": "obwohl"
  },
  {
    "word": "passer",
    "translation": "vorbeigehen, vergehen (zeitlich)"
  },
  {
    "word": "le mal du pays",
    "translation": "das Heimweh"
  },
  {
    "word": "par contre",
    "translation": "jedoch, allerdings"
  },
  {
    "word": "avoir mal (à)",
    "translation": "Schmerzen haben (an/am)"
  },
  {
    "word": "le ventre",
    "translation": "der Bauch"
  },
  {
    "word": "l’eau gazeuse",
    "add": "f.", 
    "translation": "das Mineralwasser mit Kohlensäure"
  },
  {
    "word": "l’eau plate",
    "add": "f.", 
    "translation": "das stille Mineralwasser"
  },
  {
    "word": "manquer",
    "translation": "fehlen, verpassen"
  },
  {
    "word": "se débrouiller",
    "translation": "zurechtkommen"
  },
  {
    "word": "forcément",
    "translation": "zwangsläufig"
  },
  {
    "word": "indépendant",
    "translation": "unabhängig"
  }
]
